onegov.shared-0.3.3-py3.6-nspkg.pth
onegov/shared/.gitignore
onegov/shared/__init__.py
onegov/shared/upgrade.py
onegov/shared/assets/js/form_dependencies.js
onegov/shared/tests/conftest.py
onegov/shared/tests/test_paths.py
onegov.shared-0.3.3.dist-info/METADATA
onegov.shared-0.3.3.dist-info/WHEEL
onegov.shared-0.3.3.dist-info/entry_points.txt
onegov.shared-0.3.3.dist-info/namespace_packages.txt
onegov.shared-0.3.3.dist-info/top_level.txt
onegov.shared-0.3.3.dist-info/RECORD
